razorpay/__init__.py
razorpay/alohomora/__init__.py
razorpay/alohomora/alohomora.py
razorpay/alohomora/cli.py
tests/__init__.py
tests/test_alohomora.py
tests/files/birdie.j2
tests/files/birdie2.j2
tests/files/birdie_env.j2
tests/files/birdie_fail.j2
tests/files/birdie_fail_multiple.j2
razorpay.alohomora-0.5.0.dist-info/METADATA
razorpay.alohomora-0.5.0.dist-info/WHEEL
razorpay.alohomora-0.5.0.dist-info/entry_points.txt
razorpay.alohomora-0.5.0.dist-info/top_level.txt
razorpay.alohomora-0.5.0.dist-info/RECORD
