Metadata-Version: 2.1
Name: razorpay.alohomora
Version: 0.5.0
Summary: Secret distribution tool, written as a wrapper on credstash
Home-page: https://github.com/razorpay/alohomora
Author: Team Razorpay
Author-email: developers@razorpay.com
License: MIT
Keywords: credstash,ansible,secrets,jinja
Platform: UNKNOWN
Requires-Python: >=3.7.0
Requires-Dist: credstash (==1.17.1)
Requires-Dist: click (>=8.1)
Requires-Dist: jinja2 (>=3.0)
